LICENSE
MANIFEST.in
setup.py
camprot/camprot.py
camprot.egg-info/PKG-INFO
camprot.egg-info/SOURCES.txt
camprot.egg-info/dependency_links.txt
camprot.egg-info/entry_points.txt
camprot.egg-info/not-zip-safe
camprot.egg-info/requires.txt
camprot.egg-info/top_level.txt
camprot/proteomics/d2p2.py
camprot/proteomics/protinfo.py
camprot/proteomics/sequence.py
camprot/scripts/annotate_rnp.py