Metadata-Version: 1.1
Name: camprot
Version: 0.0.13
Summary: camprot: Tools for Computational proteomics
Home-page: https://github.com/TomSmithCGAT/CamProt
Author: Tom Smith
Author-email: tss38@cam.ac.uk
License: MIT
Download-URL: https://github.com/TomSmithCGAT/CamProt/tarball/0.0.13
Keywords: computational proteomics
Platform: any
Classifier: Development Status :: 3 - Alpha
Classifier: Intended Audience :: Science/Research
Classifier: Intended Audience :: Developers
Classifier: License :: OSI Approved
Classifier: Programming Language :: Python
Classifier: Topic :: Software Development
Classifier: Topic :: Scientific/Engineering
Classifier: Operating System :: POSIX
Classifier: Operating System :: Unix
Classifier: Operating System :: MacOS
Classifier: Operating System :: Microsoft
